griffe_warnings_deprecated-1.1.0.dist-info/METADATA
griffe_warnings_deprecated-1.1.0.dist-info/WHEEL
griffe_warnings_deprecated-1.1.0.dist-info/entry_points.txt
griffe_warnings_deprecated-1.1.0.dist-info/licenses/LICENSE
griffe_warnings_deprecated/__init__.py
griffe_warnings_deprecated/debug.py
griffe_warnings_deprecated/extension.py
griffe_warnings_deprecated/py.typed
griffe_warnings_deprecated-1.1.0.dist-info/RECORD
