Metadata-Version: 2.1
Name: griffe-warnings-deprecated
Version: 1.1.0
Summary: Griffe extension for `@warnings.deprecated` (PEP 702).
Author-Email: =?utf-8?q?Timoth=C3=A9e_Mazzucotelli?= <dev@pawamoy.fr>
License: ISC
Classifier: Development Status :: 4 - Beta
Classifier: Intended Audience :: Developers
Classifier: Programming Language :: Python
Classifier: Programming Language :: Python :: 3
Classifier: Programming Language :: Python :: 3 :: Only
Classifier: Programming Language :: Python :: 3.9
Classifier: Programming Language :: Python :: 3.10
Classifier: Programming Language :: Python :: 3.11
Classifier: Programming Language :: Python :: 3.12
Classifier: Programming Language :: Python :: 3.13
Classifier: Programming Language :: Python :: 3.14
Classifier: Topic :: Documentation
Classifier: Topic :: Software Development
Classifier: Topic :: Utilities
Classifier: Typing :: Typed
Project-URL: Homepage, https://mkdocstrings.github.io/griffe-warnings-deprecated
Project-URL: Documentation, https://mkdocstrings.github.io/griffe-warnings-deprecated
Project-URL: Changelog, https://mkdocstrings.github.io/griffe-warnings-deprecated/changelog
Project-URL: Repository, https://github.com/mkdocstrings/griffe-warnings-deprecated
Project-URL: Issues, https://github.com/mkdocstrings/griffe-warnings-deprecated/issues
Project-URL: Discussions, https://github.com/mkdocstrings/griffe-warnings-deprecated/discussions
Project-URL: Gitter, https://gitter.im/mkdocstrings/griffe-warnings-deprecated
Project-URL: Funding, https://github.com/sponsors/pawamoy
Requires-Python: >=3.9
Requires-Dist: griffe>=0.49
